Workbook

Sheet Übersicht
A1: Sheet | B1: Typ | C1: Beschreibung | D1: Quelle
A2: Übersicht | B2: Eigene Datei | C2: Übersicht aller relevanten Dateien
A3: KPI | B3: Eigene Berechnung | C3: Kernergebnisse aus der Kalkulation
A4: Annahmen | B4: Eigene Berechnung | C4: Zentrale Annahmen für Tarif, Beschaffung, reBAP
A5: Kunde-SLP_Tagesmodell | B5: Eigene Berechnung | C5: Tagesgenaues Deckungsbeitragsmodell 2025
A6: Sensitivität | B6: Eigene Berechnung | C6: Sensitivitätsanalyse Profilabweichung × reBAP-Stress
A7: BDEW-H25 Tagessummen | B7: Eigene Berechnung (aus Quelldaten) | C7: Aggregierte Tagessummen aus dem BDEW H25-Profil
A8: Quelle_BDEW_H25 | B8: Quelldaten (unverändert) | C8: Original BDEW-Profildatei (bdew.de) | D8: https://www.bdew.de/energie/standardlastprofile-strom/
A9: Quelle_BDEW_Dynamisierung | B9: Quelldaten (unverändert) | C9: Original-Blatt "Dynamisierung" mit Koeffizienten und Anwendungshinweisen zur Dynamisierungsfunktion (H25/P25/S25) | D9: https://www.bdew.de/energie/standardlastprofile-strom/
A10: Quelle_SMARD_Preise_2025 | B10: Quelldaten (unverändert) | C10: SMARD Day-Ahead-Preise 2025 (smard.de) | D10: https://www.smard.de/en/downloadcenter/download-market-data/?downloadAttributes=%7B%22superCategoryId%22:3,%22subcategoryId%22:8,%22regionId%22:%22DE-LU%22,%22resolution%22:%22day%22,%22fileType%22:%22XLS%22,%22from%22:1735686000000,%22to%22:1767221999999%7D
A11: Feiertage_Hessen_2025 | B11: Quelldaten (unverändert) | C11: Feiertage in Hessen 2025 | D11: https://www.arbeitstage.org/hessen/feiertage-2025-hessen/#google_vignette

Sheet KPI
A1: Wichtige Ergebnisse / KPIs
A3: Jahres Erlöse | B3: =Tabelle1[[#Totals],[Erlöse (€)]] -> 650000
A4: Beschaffungskosten_fix | B4: =Tabelle1[[#Totals],[Beschaffungskosten_fix]] -> 273000
A5: Beschaffungskosten_indexiert | B5: =Tabelle1[[#Totals],[Beschaffungskosten_indexiert]] -> 134781.63
A6: Gesamte Ausgleichsenergie Kosten für Jahr 2025 | B6: =Tabelle1[[#Totals],[Kosten_Ausgleichsenerge]] -> 27860.103
A7: Jahres Deckungsbeitrag | B7: =Tabelle1[[#Totals],[Deckungsbeitrag]] -> 214358.26
A8: Jahres Deckungsbeitrag-Marge % | B8: =B7/B3 -> 0.32978195

Sheet Annahmen
A1: Liste der Annahmen
C3: Einheit | D3: Quelle/Anmerkung
A4: Kundenprofil | B4: H25 | D4: BDEW für Haushaltskunden
A5: Jahresvolumen | B5: 5000 | C5: MWh | D5: Exemplar. Entspricht 1400 Haushalte mit Verbrauch von 3500 kWh/Jahr
A6: Endkundentarif | B6: 130 | C6: €/MWh | D6: Vertriebs/Margenanteil (Netzentgelte, Stromsteuer sind ausgenommen)
A7: Beschaffung Fixpreisanteil | B7: 0.7 | D7: Anteil des Portfoliovolumens, der zum Fixpreis gemacht wurde
A8: Beschaffung Fixpreistarif | B8: 78 | C8: €/MWh | D8: Angenommener Preis
A9: Profil_Abweichung | B9: 0.05 | D9: Angenommener Abweichung zwischen prognostiziertem und tatsächlicher Jahresverbrauch
A10: reBAP_Spread Annahme | B10: 8 | C10: €/MWh | D10: Angenommener durchschnittlicher Aufschlag von reBAP gegenüber dem Indexpreis in Normalzeiten
A11: reBAP_Spread Aufschlag | B11: 120 | C11: €/MWh | D11: Zusätzlicher Aufschlag an Stress-Tagen (Top-/Bottom-5%-Tage der Tage des tatsächlichen Tagesverbrauchs (BDEW H25).)

Sheet Kunde-SLP_Tagesmodell
A1: Datum | B1: Wochentag | C1: Monat | D1: Tag_des_Jahres | E1: Label (WT/FT/SA) | F1: Profilwert (kWh) | G1: Dynamisierungsfaktor | H1: Profilwert Dynamisiert (kWh) | I1: Tagesverbrauch (MWh) | J1: Tariff (€/MWh) | K1: Erlöse (€) | L1: Volumen_fix | M1: Volumen_indexiert | N1: Beschaffungspreis_fix | O1: Beschaffungspreis_indexiert | P1: Beschaffungskosten_fix | Q1: Beschaffungskosten_indexiert | R1: Profil Abweichung | S1: Volumen_Abweichung | T1: Stress_Tag | U1: reBAP_Preis (€/MWh) | V1: Kosten_Ausgleichsenerge | W1: Deckungsbeitrag | Y1: Wichtige Hinweise:
A2: 45658 | B2: =TEXT(A2,"TTT") -> Mi | C2: =MONTH(A2) -> 1 | D2: 1 | E2: =IF(OR(COUNTIF(Feiertage_Hessen_2025!$C$4:$C$13,A2)>0,WEEKDAY(A2,2)=7),"FT",IF(WEEKDAY(A2,2)=6,"SA","WT")) -> FT | F2: =INDEX('BDEW-H25 Tagessummen'!$C$4:$C$39, MATCH(C2&"_"&E2, 'BDEW-H25 Tagessummen'!$D$4:$D$39, 0)) -> 2903.033 | G2: =-3.92*10^-10*D2^4+3.2*10^-7*D2^3-7.02*10^-5*D2^2+2.1*10^-3*D2+1.24 -> 1.2420301 | H2: =Tabelle1[[#This Row],[Profilwert (kWh)]]*Tabelle1[[#This Row],[Dynamisierungsfaktor]] -> 3605.6544 | I2: =Annahmen!$B$5*(H2/SUM($H$2:$H$366)) -> 18.03607 | J2: =Annahmen!$B$6 -> 130 | K2: =I2*J2 -> 2344.6891 | L2: =I2*Annahmen!$B$7 -> 12.625249 | M2: =I2*(1-Annahmen!$B$7) -> 5.410821 | N2: =Annahmen!$B$8 -> 78 | O2: =INDEX(Quelle_SMARD_Preise_2025!$C$11:$C$375, MATCH($A2,Quelle_SMARD_Preise_2025!$A$11:$A$375, 0)) -> 0.95 | P2: =L2*N2 -> 984.76942 | Q2: =M2*Tabelle1[[#This Row],[Beschaffungspreis_indexiert]] -> 5.1402799 | R2: =Annahmen!$B$9 -> 0.05 | S2: =R2*I2 -> 0.9018035 | T2: =IF(OR(I2>=PERCENTILE($I$2:$I$366,0.95),I2<=PERCENTILE($I$2:$I$366,0.05)),1,0) -> 1 | U2: =$O2+Annahmen!$B$10+(T2*Annahmen!$B$11) -> 128.95 | V2: =ABS(S2)*U2 -> 116.28756 | W2: =K2-P2-Q2-V2 -> 1238.4918 | Y2: Der reBAP-Preis berechnet sich wie folgt:
A3: 45659 | B3: =TEXT(A3,"TTT") -> Do | C3: =MONTH(A3) -> 1 | D3: 2 | E3: =IF(OR(COUNTIF(Feiertage_Hessen_2025!$C$4:$C$13,A3)>0,WEEKDAY(A3,2)=7),"FT",IF(WEEKDAY(A3,2)=6,"SA","WT")) -> WT | F3: =INDEX('BDEW-H25 Tagessummen'!$C$4:$C$39, MATCH(C3&"_"&E3, 'BDEW-H25 Tagessummen'!$D$4:$D$39, 0)) -> 2476.45 | G3: =-3.92*10^-10*D3^4+3.2*10^-7*D3^3-7.02*10^-5*D3^2+2.1*10^-3*D3+1.24 -> 1.2439218 | H3: =Tabelle1[[#This Row],[Profilwert (kWh)]]*Tabelle1[[#This Row],[Dynamisierungsfaktor]] -> 3080.51 | I3: =Annahmen!$B$5*(H3/SUM($H$2:$H$366)) -> 15.409212 | J3: =Annahmen!$B$6 -> 130 | K3: =I3*J3 -> 2003.1976 | L3: =I3*Annahmen!$B$7 -> 10.786449 | M3: =I3*(1-Annahmen!$B$7) -> 4.6227637 | N3: =Annahmen!$B$8 -> 78 | O3: =INDEX(Quelle_SMARD_Preise_2025!$C$11:$C$375, MATCH($A3,Quelle_SMARD_Preise_2025!$A$11:$A$375, 0)) -> 92.91 | P3: =L3*N3 -> 841.34299 | Q3: =M3*O2 -> 4.3916255 | R3: =Annahmen!$B$9 -> 0.05 | S3: =R3*I3 -> 0.77046061 | T3: =IF(OR(I3>=PERCENTILE($I$2:$I$366,0.95),I3<=PERCENTILE($I$2:$I$366,0.05)),1,0) -> 0 | U3: =$O3+Annahmen!$B$10+(T3*Annahmen!$B$11) -> 100.91 | V3: =ABS(S3)*U3 -> 77.747181 | W3: =K3-P3-Q3-V3 -> 1079.7158 | Y3: Indexpreis (Spotpreis) + reBAP-Preis für Ausgleichsenergie + reBAP-Preis für Stress-Tage (an denen der Verbrauch zu den obersten bzw. untersten 5 % gehörte)
A4: 45660 | B4: =TEXT(A4,"TTT") -> Fr | C4: =MONTH(A4) -> 1 | D4: 3 | E4: =IF(OR(COUNTIF(Feiertage_Hessen_2025!$C$4:$C$13,A4)>0,WEEKDAY(A4,2)=7),"FT",IF(WEEKDAY(A4,2)=6,"SA","WT")) -> WT | F4: =INDEX('BDEW-H25 Tagessummen'!$C$4:$C$39, MATCH(C4&"_"&E4, 'BDEW-H25 Tagessummen'!$D$4:$D$39, 0)) -> 2476.45 | G4: =-3.92*10^-10*D4^4+3.2*10^-7*D4^3-7.02*10^-5*D4^2+2.1*10^-3*D4+1.24 -> 1.2456768 | H4: =Tabelle1[[#This Row],[Profilwert (kWh)]]*Tabelle1[[#This Row],[Dynamisierungsfaktor]] -> 3084.8563 | I4: =Annahmen!$B$5*(H4/SUM($H$2:$H$366)) -> 15.430953 | J4: =Annahmen!$B$6 -> 130 | K4: =I4*J4 -> 2006.0239 | L4: =I4*Annahmen!$B$7 -> 10.801667 | M4: =I4*(1-Annahmen!$B$7) -> 4.629286 | N4: =Annahmen!$B$8 -> 78 | O4: =INDEX(Quelle_SMARD_Preise_2025!$C$11:$C$375, MATCH($A4,Quelle_SMARD_Preise_2025!$A$11:$A$375, 0)) -> 89.94 | P4: =L4*N4 -> 842.53004 | Q4: =M4*O4 -> 416.35798 | R4: =Annahmen!$B$9 -> 0.05 | S4: =R4*I4 -> 0.77154766 | T4: =IF(OR(I4>=PERCENTILE($I$2:$I$366,0.95),I4<=PERCENTILE($I$2:$I$366,0.05)),1,0) -> 0 | U4: =$O4+Annahmen!$B$10+(T4*Annahmen!$B$11) -> 97.94 | V4: =ABS(S4)*U4 -> 75.565378 | W4: =K4-P4-Q4-V4 -> 671.57051
A5: 45661 | B5: =TEXT(A5,"TTT") -> Sa | C5: =MONTH(A5) -> 1 | D5: 4 | E5: =IF(OR(COUNTIF(Feiertage_Hessen_2025!$C$4:$C$13,A5)>0,WEEKDAY(A5,2)=7),"FT",IF(WEEKDAY(A5,2)=6,"SA","WT")) -> SA | F5: =INDEX('BDEW-H25 Tagessummen'!$C$4:$C$39, MATCH(C5&"_"&E5, 'BDEW-H25 Tagessummen'!$D$4:$D$39, 0)) -> 2842.961 | G5: =-3.92*10^-10*D5^4+3.2*10^-7*D5^3-7.02*10^-5*D5^2+2.1*10^-3*D5+1.24 -> 1.2472972 | H5: =Tabelle1[[#This Row],[Profilwert (kWh)]]*Tabelle1[[#This Row],[Dynamisierungsfaktor]] -> 3546.0172 | I5: =Annahmen!$B$5*(H5/SUM($H$2:$H$366)) -> 17.737755 | J5: =Annahmen!$B$6 -> 130 | K5: =I5*J5 -> 2305.9082 | L5: =I5*Annahmen!$B$7 -> 12.416429 | M5: =I5*(1-Annahmen!$B$7) -> 5.3213265 | N5: =Annahmen!$B$8 -> 78 | O5: =INDEX(Quelle_SMARD_Preise_2025!$C$11:$C$375, MATCH($A5,Quelle_SMARD_Preise_2025!$A$11:$A$375, 0)) -> 120.79 | P5: =L5*N5 -> 968.48143 | Q5: =M5*O5 -> 642.76303 | R5: =Annahmen!$B$9 -> 0.05 | S5: =R5*I5 -> 0.88688775 | T5: =IF(OR(I5>=PERCENTILE($I$2:$I$366,0.95),I5<=PERCENTILE($I$2:$I$366,0.05)),1,0) -> 1 | U5: =$O5+Annahmen!$B$10+(T5*Annahmen!$B$11) -> 248.79 | V5: =ABS(S5)*U5 -> 220.6488 | W5: =K5-P5-Q5-V5 -> 474.0149
A6: 45662 | B6: =TEXT(A6,"TTT") -> So | C6: =MONTH(A6) -> 1 | D6: 5 | E6: =IF(OR(COUNTIF(Feiertage_Hessen_2025!$C$4:$C$13,A6)>0,WEEKDAY(A6,2)=7),"FT",IF(WEEKDAY(A6,2)=6,"SA","WT")) -> FT | F6: =INDEX('BDEW-H25 Tagessummen'!$C$4:$C$39, MATCH(C6&"_"&E6, 'BDEW-H25 Tagessummen'!$D$4:$D$39, 0)) -> 2903.033 | G6: =-3.92*10^-10*D6^4+3.2*10^-7*D6^3-7.02*10^-5*D6^2+2.1*10^-3*D6+1.24 -> 1.2487848 | H6: =Tabelle1[[#This Row],[Profilwert (kWh)]]*Tabelle1[[#This Row],[Dynamisierungsfaktor]] -> 3625.2634 | I6: =Annahmen!$B$5*(H6/SUM($H$2:$H$366)) -> 18.134157 | J6: =Annahmen!$B$6 -> 130 | K6: =I6*J6 -> 2357.4404 | L6: =I6*Annahmen!$B$7 -> 12.69391 | M6: =I6*(1-Annahmen!$B$7) -> 5.4402471 | N6: =Annahmen!$B$8 -> 78 | O6: =INDEX(Quelle_SMARD_Preise_2025!$C$11:$C$375, MATCH($A6,Quelle_SMARD_Preise_2025!$A$11:$A$375, 0)) -> 72.24 | P6: =L6*N6 -> 990.12497 | Q6: =M6*O6 -> 393.00345 | R6: =Annahmen!$B$9 -> 0.05 | S6: =R6*I6 -> 0.90670785 | T6: =IF(OR(I6>=PERCENTILE($I$2:$I$366,0.95),I6<=PERCENTILE($I$2:$I$366,0.05)),1,0) -> 1 | U6: =$O6+Annahmen!$B$10+(T6*Annahmen!$B$11) -> 200.24 | V6: =ABS(S6)*U6 -> 181.55918 | W6: =K6-P6-Q6-V6 -> 792.75281
A7: 45663 | B7: =TEXT(A7,"TTT") -> Mo | C7: =MONTH(A7) -> 1 | D7: 6 | E7: =IF(OR(COUNTIF(Feiertage_Hessen_2025!$C$4:$C$13,A7)>0,WEEKDAY(A7,2)=7),"FT",IF(WEEKDAY(A7,2)=6,"SA","WT")) -> WT | F7: =INDEX('BDEW-H25 Tagessummen'!$C$4:$C$39, MATCH(C7&"_"&E7, 'BDEW-H25 Tagessummen'!$D$4:$D$39, 0)) -> 2476.45 | G7: =-3.92*10^-10*D7^4+3.2*10^-7*D7^3-7.02*10^-5*D7^2+2.1*10^-3*D7+1.24 -> 1.2501414 | H7: =Tabelle1[[#This Row],[Profilwert (kWh)]]*Tabelle1[[#This Row],[Dynamisierungsfaktor]] -> 3095.9127 | I7: =Annahmen!$B$5*(H7/SUM($H$2:$H$366)) -> 15.486259 | J7: =Annahmen!$B$6 -> 130 | K7: =I7*J7 -> 2013.2137 | L7: =I7*Annahmen!$B$7 -> 10.840381 | M7: =I7*(1-Annahmen!$B$7) -> 4.6458777 | N7: =Annahmen!$B$8 -> 78 | O7: =INDEX(Quelle_SMARD_Preise_2025!$C$11:$C$375, MATCH($A7,Quelle_SMARD_Preise_2025!$A$11:$A$375, 0)) -> 25.16 | P7: =L7*N7 -> 845.54974 | Q7: =M7*O7 -> 116.89028 | R7: =Annahmen!$B$9 -> 0.05 | S7: =R7*I7 -> 0.77431295 | T7: =IF(OR(I7>=PERCENTILE($I$2:$I$366,0.95),I7<=PERCENTILE($I$2:$I$366,0.05)),1,0) -> 0 | U7: =$O7+Annahmen!$B$10+(T7*Annahmen!$B$11) -> 33.16 | V7: =ABS(S7)*U7 -> 25.676217 | W7: =K7-P7-Q7-V7 -> 1025.0974
A8: 45664 | B8: =TEXT(A8,"TTT") -> Di | C8: =MONTH(A8) -> 1 | D8: 7 | E8: =IF(OR(COUNTIF(Feiertage_Hessen_2025!$C$4:$C$13,A8)>0,WEEKDAY(A8,2)=7),"FT",IF(WEEKDAY(A8,2)=6,"SA","WT")) -> WT | F8: =INDEX('BDEW-H25 Tagessummen'!$C$4:$C$39, MATCH(C8&"_"&E8, 'BDEW-H25 Tagessummen'!$D$4:$D$39, 0)) -> 2476.45 | G8: =-3.92*10^-10*D8^4+3.2*10^-7*D8^3-7.02*10^-5*D8^2+2.1*10^-3*D8+1.24 -> 1.251369 | H8: =Tabelle1[[#This Row],[Profilwert (kWh)]]*Tabelle1[[#This Row],[Dynamisierungsfaktor]] -> 3098.9528 | I8: =Annahmen!$B$5*(H8/SUM($H$2:$H$366)) -> 15.501466 | J8: =Annahmen!$B$6 -> 130 | K8: =I8*J8 -> 2015.1906 | L8: =I8*Annahmen!$B$7 -> 10.851026 | M8: =I8*(1-Annahmen!$B$7) -> 4.6504398 | N8: =Annahmen!$B$8 -> 78 | O8: =INDEX(Quelle_SMARD_Preise_2025!$C$11:$C$375, MATCH($A8,Quelle_SMARD_Preise_2025!$A$11:$A$375, 0)) -> 58.29 | P8: =L8*N8 -> 846.38005 | Q8: =M8*O8 -> 271.07414 | R8: =Annahmen!$B$9 -> 0.05 | S8: =R8*I8 -> 0.7750733 | T8: =IF(OR(I8>=PERCENTILE($I$2:$I$366,0.95),I8<=PERCENTILE($I$2:$I$366,0.05)),1,0) -> 0 | U8: =$O8+Annahmen!$B$10+(T8*Annahmen!$B$11) -> 66.29 | V8: =ABS(S8)*U8 -> 51.379609 | W8: =K8-P8-Q8-V8 -> 846.35679
A9: 45665 | B9: =TEXT(A9,"TTT") -> Mi | C9: =MONTH(A9) -> 1 | D9: 8 | E9: =IF(OR(COUNTIF(Feiertage_Hessen_2025!$C$4:$C$13,A9)>0,WEEKDAY(A9,2)=7),"FT",IF(WEEKDAY(A9,2)=6,"SA","WT")) -> WT | F9: =INDEX('BDEW-H25 Tagessummen'!$C$4:$C$39, MATCH(C9&"_"&E9, 'BDEW-H25 Tagessummen'!$D$4:$D$39, 0)) -> 2476.45 | G9: =-3.92*10^-10*D9^4+3.2*10^-7*D9^3-7.02*10^-5*D9^2+2.1*10^-3*D9+1.24 -> 1.2524694 | H9: =Tabelle1[[#This Row],[Profilwert (kWh)]]*Tabelle1[[#This Row],[Dynamisierungsfaktor]] -> 3101.6779 | I9: =Annahmen!$B$5*(H9/SUM($H$2:$H$366)) -> 15.515098 | J9: =Annahmen!$B$6 -> 130 | K9: =I9*J9 -> 2016.9627 | L9: =I9*Annahmen!$B$7 -> 10.860568 | M9: =I9*(1-Annahmen!$B$7) -> 4.6545293 | N9: =Annahmen!$B$8 -> 78 | O9: =INDEX(Quelle_SMARD_Preise_2025!$C$11:$C$375, MATCH($A9,Quelle_SMARD_Preise_2025!$A$11:$A$375, 0)) -> 104.53 | P9: =L9*N9 -> 847.12433 | Q9: =M9*O9 -> 486.53794 | R9: =Annahmen!$B$9 -> 0.05 | S9: =R9*I9 -> 0.77575488 | T9: =IF(OR(I9>=PERCENTILE($I$2:$I$366,0.95),I9<=PERCENTILE($I$2:$I$366,0.05)),1,0) -> 0 | U9: =$O9+Annahmen!$B$10+(T9*Annahmen!$B$11) -> 112.53 | V9: =ABS(S9)*U9 -> 87.295697 | W9: =K9-P9-Q9-V9 -> 596.00472
A10: 45666 | B10: =TEXT(A10,"TTT") -> Do | C10: =MONTH(A10) -> 1 | D10: 9 | E10: =IF(OR(COUNTIF(Feiertage_Hessen_2025!$C$4:$C$13,A10)>0,WEEKDAY(A10,2)=7),"FT",IF(WEEKDAY(A10,2)=6,"SA","WT")) -> WT | F10: =INDEX('BDEW-H25 Tagessummen'!$C$4:$C$39, MATCH(C10&"_"&E10, 'BDEW-H25 Tagessummen'!$D$4:$D$39, 0)) -> 2476.45 | G10: =-3.92*10^-10*D10^4+3.2*10^-7*D10^3-7.02*10^-5*D10^2+2.1*10^-3*D10+1.24 -> 1.2534445 | H10: =Tabelle1[[#This Row],[Profilwert (kWh)]]*Tabelle1[[#This Row],[Dynamisierungsfaktor]] -> 3104.0927 | I10: =Annahmen!$B$5*(H10/SUM($H$2:$H$366)) -> 15.527176 | J10: =Annahmen!$B$6 -> 130 | K10: =I10*J10 -> 2018.5329 | L10: =I10*Annahmen!$B$7 -> 10.869023 | M10: =I10*(1-Annahmen!$B$7) -> 4.6581529 | N10: =Annahmen!$B$8 -> 78 | O10: =INDEX(Quelle_SMARD_Preise_2025!$C$11:$C$375, MATCH($A10,Quelle_SMARD_Preise_2025!$A$11:$A$375, 0)) -> 121.53 | P10: =L10*N10 -> 847.78383 | Q10: =M10*O10 -> 566.10532 | R10: =Annahmen!$B$9 -> 0.05 | S10: =R10*I10 -> 0.77635882 | T10: =IF(OR(I10>=PERCENTILE($I$2:$I$366,0.95),I10<=PERCENTILE($I$2:$I$366,0.05)),1,0) -> 0 | U10: =$O10+Annahmen!$B$10+(T10*Annahmen!$B$11) -> 129.53 | V10: =ABS(S10)*U10 -> 100.56176 | W10: =K10-P10-Q10-V10 -> 504.08202
A11: 45667 | B11: =TEXT(A11,"TTT") -> Fr | C11: =MONTH(A11) -> 1 | D11: 10 | E11: =IF(OR(COUNTIF(Feiertage_Hessen_2025!$C$4:$C$13,A11)>0,WEEKDAY(A11,2)=7),"FT",IF(WEEKDAY(A11,2)=6,"SA","WT")) -> WT | F11: =INDEX('BDEW-H25 Tagessummen'!$C$4:$C$39, MATCH(C11&"_"&E11, 'BDEW-H25 Tagessummen'!$D$4:$D$39, 0)) -> 2476.45 | G11: =-3.92*10^-10*D11^4+3.2*10^-7*D11^3-7.02*10^-5*D11^2+2.1*10^-3*D11+1.24 -> 1.2542961 | H11: =Tabelle1[[#This Row],[Profilwert (kWh)]]*Tabelle1[[#This Row],[Dynamisierungsfaktor]] -> 3106.2015 | I11: =Annahmen!$B$5*(H11/SUM($H$2:$H$366)) -> 15.537725 | J11: =Annahmen!$B$6 -> 130 | K11: =I11*J11 -> 2019.9043 | L11: =I11*Annahmen!$B$7 -> 10.876408 | M11: =I11*(1-Annahmen!$B$7) -> 4.6613176 | N11: =Annahmen!$B$8 -> 78 | O11: =INDEX(Quelle_SMARD_Preise_2025!$C$11:$C$375, MATCH($A11,Quelle_SMARD_Preise_2025!$A$11:$A$375, 0)) -> 112.43 | P11: =L11*N11 -> 848.3598 | Q11: =M11*O11 -> 524.07194 | R11: =Annahmen!$B$9 -> 0.05 | S11: =R11*I11 -> 0.77688627 | T11: =IF(OR(I11>=PERCENTILE($I$2:$I$366,0.95),I11<=PERCENTILE($I$2:$I$366,0.05)),1,0) -> 0 | U11: =$O11+Annahmen!$B$10+(T11*Annahmen!$B$11) -> 120.43 | V11: =ABS(S11)*U11 -> 93.560413 | W11: =K11-P11-Q11-V11 -> 553.91214
A12: 45668 | B12: =TEXT(A12,"TTT") -> Sa | C12: =MONTH(A12) -> 1 | D12: 11 | E12: =IF(OR(COUNTIF(Feiertage_Hessen_2025!$C$4:$C$13,A12)>0,WEEKDAY(A12,2)=7),"FT",IF(WEEKDAY(A12,2)=6,"SA","WT")) -> SA | F12: =INDEX('BDEW-H25 Tagessummen'!$C$4:$C$39, MATCH(C12&"_"&E12, 'BDEW-H25 Tagessummen'!$D$4:$D$39, 0)) -> 2842.961 | G12: =-3.92*10^-10*D12^4+3.2*10^-7*D12^3-7.02*10^-5*D12^2+2.1*10^-3*D12+1.24 -> 1.255026 | H12: =Tabelle1[[#This Row],[Profilwert (kWh)]]*Tabelle1[[#This Row],[Dynamisierungsfaktor]] -> 3567.9899 | I12: =Annahmen!$B$5*(H12/SUM($H$2:$H$366)) -> 17.847666 | J12: =Annahmen!$B$6 -> 130 | K12: =I12*J12 -> 2320.1966 | L12: =I12*Annahmen!$B$7 -> 12.493366 | M12: =I12*(1-Annahmen!$B$7) -> 5.3542998 | N12: =Annahmen!$B$8 -> 78 | O12: =INDEX(Quelle_SMARD_Preise_2025!$C$11:$C$375, MATCH($A12,Quelle_SMARD_Preise_2025!$A$11:$A$375, 0)) -> 101.89 | P12: =L12*N12 -> 974.48256 | Q12: =M12*O12 -> 545.54961 | R12: =Annahmen!$B$9 -> 0.05 | S12: =R12*I12 -> 0.8923833 | T12: =IF(OR(I12>=PERCENTILE($I$2:$I$366,0.95),I12<=PERCENTILE($I$2:$I$366,0.05)),1,0) -> 1 | U12: =$O12+Annahmen!$B$10+(T12*Annahmen!$B$11) -> 229.89 | V12: =ABS(S12)*U12 -> 205.15 | W12: =K12-P12-Q12-V12 -> 595.01441
A13: 45669 | B13: =TEXT(A13,"TTT") -> So | C13: =MONTH(A13) -> 1 | D13: 12 | E13: =IF(OR(COUNTIF(Feiertage_Hessen_2025!$C$4:$C$13,A13)>0,WEEKDAY(A13,2)=7),"FT",IF(WEEKDAY(A13,2)=6,"SA","WT")) -> FT | F13: =INDEX('BDEW-H25 Tagessummen'!$C$4:$C$39, MATCH(C13&"_"&E13, 'BDEW-H25 Tagessummen'!$D$4:$D$39, 0)) -> 2903.033 | G13: =-3.92*10^-10*D13^4+3.2*10^-7*D13^3-7.02*10^-5*D13^2+2.1*10^-3*D13+1.24 -> 1.255636 | H13: =Tabelle1[[#This Row],[Profilwert (kWh)]]*Tabelle1[[#This Row],[Dynamisierungsfaktor]] -> 3645.1528 | I13: =Annahmen!$B$5*(H13/SUM($H$2:$H$366)) -> 18.233647 | J13: =Annahmen!$B$6 -> 130 | K13: =I13*J13 -> 2370.3742 | L13: =I13*Annahmen!$B$7 -> 12.763553 | M13: =I13*(1-Annahmen!$B$7) -> 5.4700942 | N13: =Annahmen!$B$8 -> 78 | O13: =INDEX(Quelle_SMARD_Preise_2025!$C$11:$C$375, MATCH($A13,Quelle_SMARD_Preise_2025!$A$11:$A$375, 0)) -> 110.07 | P13: =L13*N13 -> 995.55715 | Q13: =M13*O13 -> 602.09327 | R13: =Annahmen!$B$9 -> 0.05 | S13: =R13*I13 -> 0.91168237 | T13: =IF(OR(I13>=PERCENTILE($I$2:$I$366,0.95),I13<=PERCENTILE($I$2:$I$366,0.05)),1,0) -> 1 | U13: =$O13+Annahmen!$B$10+(T13*Annahmen!$B$11) -> 238.07 | V13: =ABS(S13)*U13 -> 217.04422 | W13: =K13-P13-Q13-V13 -> 555.67952
A14: 45670 | B14: =TEXT(A14,"TTT") -> Mo | C14: =MONTH(A14) -> 1 | D14: 13 | E14: =IF(OR(COUNTIF(Feiertage_Hessen_2025!$C$4:$C$13,A14)>0,WEEKDAY(A14,2)=7),"FT",IF(WEEKDAY(A14,2)=6,"SA","WT")) -> WT | F14: =INDEX('BDEW-H25 Tagessummen'!$C$4:$C$39, MATCH(C14&"_"&E14, 'BDEW-H25 Tagessummen'!$D$4:$D$39, 0)) -> 2476.45 | G14: =-3.92*10^-10*D14^4+3.2*10^-7*D14^3-7.02*10^-5*D14^2+2.1*10^-3*D14+1.24 -> 1.256128 | H14: =Tabelle1[[#This Row],[Profilwert (kWh)]]*Tabelle1[[#This Row],[Dynamisierungsfaktor]] -> 3110.7383 | I14: =Annahmen!$B$5*(H14/SUM($H$2:$H$366)) -> 15.560419 | J14: =Annahmen!$B$6 -> 130 | K14: =I14*J14 -> 2022.8545 | L14: =I14*Annahmen!$B$7 -> 10.892293 | M14: =I14*(1-Annahmen!$B$7) -> 4.6681257 | N14: =Annahmen!$B$8 -> 78 | O14: =INDEX(Quelle_SMARD_Preise_2025!$C$11:$C$375, MATCH($A14,Quelle_SMARD_Preise_2025!$A$11:$A$375, 0)) -> 129.2 | P14: =L14*N14 -> 849.59888 | Q14: =M14*O14 -> 603.12184 | R14: =Annahmen!$B$9 -> 0.05 | S14: =R14*I14 -> 0.77802095 | T14: =IF(OR(I14>=PERCENTILE($I$2:$I$366,0.95),I14<=PERCENTILE($I$2:$I$366,0.05)),1,0) -> 0 | U14: =$O14+Annahmen!$B$10+(T14*Annahmen!$B$11) -> 137.2 | V14: =ABS(S14)*U14 -> 106.74447 | W14: =K14-P14-Q14-V14 -> 463.38928
A15: 45671 | B15: =TEXT(A15,"TTT") -> Di | C15: =MONTH(A15) -> 1 | D15: 14 | E15: =IF(OR(COUNTIF(Feiertage_Hessen_2025!$C$4:$C$13,A15)>0,WEEKDAY(A15,2)=7),"FT",IF(WEEKDAY(A15,2)=6,"SA","WT")) -> WT | F15: =INDEX('BDEW-H25 Tagessummen'!$C$4:$C$39, MATCH(C15&"_"&E15, 'BDEW-H25 Tagessummen'!$D$4:$D$39, 0)) -> 2476.45 | G15: =-3.92*10^-10*D15^4+3.2*10^-7*D15^3-7.02*10^-5*D15^2+2.1*10^-3*D15+1.24 -> 1.2565038 | H15: =Tabelle1[[#This Row],[Profilwert (kWh)]]*Tabelle1[[#This Row],[Dynamisierungsfaktor]] -> 3111.6689 | I15: =Annahmen!$B$5*(H15/SUM($H$2:$H$366)) -> 15.565074 | J15: =Annahmen!$B$6 -> 130 | K15: =I15*J15 -> 2023.4596 | L15: =I15*Annahmen!$B$7 -> 10.895552 | M15: =I15*(1-Annahmen!$B$7) -> 4.6695222 | N15: =Annahmen!$B$8 -> 78 | O15: =INDEX(Quelle_SMARD_Preise_2025!$C$11:$C$375, MATCH($A15,Quelle_SMARD_Preise_2025!$A$11:$A$375, 0)) -> 126.82 | P15: =L15*N15 -> 849.85304 | Q15: =M15*O15 -> 592.1888 | R15: =Annahmen!$B$9 -> 0.05 | S15: =R15*I15 -> 0.7782537 | T15: =IF(OR(I15>=PERCENTILE($I$2:$I$366,0.95),I15<=PERCENTILE($I$2:$I$366,0.05)),1,0) -> 0 | U15: =$O15+Annahmen!$B$10+(T15*Annahmen!$B$11) -> 134.82 | V15: =ABS(S15)*U15 -> 104.92416 | W15: =K15-P15-Q15-V15 -> 476.49361
... A366: 46022 | B366: =TEXT(A366,"TTT") -> Mi | C366: =MONTH(A366) -> 12 | D366: 365 | E366: =IF(OR(COUNTIF(Feiertage_Hessen_2025!$C$4:$C$13,A366)>0,WEEKDAY(A366,2)=7),"FT",IF(WEEKDAY(A366,2)=6,"SA","WT")) -> WT | F366: =INDEX('BDEW-H25 Tagessummen'!$C$4:$C$39, MATCH(C366&"_"&E366, 'BDEW-H25 Tagessummen'!$D$4:$D$39, 0)) -> 2536.519 | G366: =-3.92*10^-10*D366^4+3.2*10^-7*D366^3-7.02*10^-5*D366^2+2.1*10^-3*D366+1.24 -> 1.257216 | H366: =Tabelle1[[#This Row],[Profilwert (kWh)]]*Tabelle1[[#This Row],[Dynamisierungsfaktor]] -> 3188.9522 | I366: =Annahmen!$B$5*(H366/SUM($H$2:$H$366)) -> 15.951657 | J366: =Annahmen!$B$6 -> 130 | K366: =I366*J366 -> 2073.7155 | L366: =I366*Annahmen!$B$7 -> 11.16616 | M366: =I366*(1-Annahmen!$B$7) -> 4.7854972 | N366: =Annahmen!$B$8 -> 78 | O366: =INDEX(Quelle_SMARD_Preise_2025!$C$11:$C$375, MATCH($A366,Quelle_SMARD_Preise_2025!$A$11:$A$375, 0)) -> 87.31 | P366: =L366*N366 -> 870.9605 | Q366: =M366*O366 -> 417.82176 | R366: =Annahmen!$B$9 -> 0.05 | S366: =R366*I366 -> 0.79758287 | T366: =IF(OR(I366>=PERCENTILE($I$2:$I$366,0.95),I366<=PERCENTILE($I$2:$I$366,0.05)),1,0) -> 0 | U366: =$O366+Annahmen!$B$10+(T366*Annahmen!$B$11) -> 95.31 | V366: =ABS(S366)*U366 -> 76.017624 | W366: =K366-P366-Q366-V366 -> 708.91558
K367: =SUM(K2:K366) -> 650000 | L367: =SUM(L2:L366) -> 3500 | M367: =SUM(M2:M366) -> 1500 | P367: =SUM(P2:P366) -> 273000 | Q367: =SUM(Q2:Q366) -> 134781.63 | V367: =SUM(V2:V366) -> 27860.103 | W367: =SUM(W2:W366) -> 214358.26 | X367: Summe

Sheet Sensitivität
A1: Sensitivität | C1: Diese Sensitivitätsanalyse untersucht, wie stark sich der Deckungsbeitrag verändert, wenn sich die Profilabweichung und der Stressaufschlag für reBAP ändern. Die Erlöse und Beschaffungskosten bleiben dabei unverändert.
C4: Stress Aufschlag (€)
A5: Profil Abweichung (%) | B5: Abweichung/Stress | C5: 0 | D5: 50 | E5: 100 | F5: 150 | G5: 200
B6: -0.2 | C6: {=SUM('Kunde-SLP_Tagesmodell'!$K$2:$K$366)-SUM('Kunde-SLP_Tagesmodell'!$P$2:$P$366)-SUM('Kunde-SLP_Tagesmodell'!$Q$2:$Q$366)-SUMPRODUCT(ABS('Kunde-SLP_Tagesmodell'!$I$2:$I$366*$B6),('Kunde-SLP_Tagesmodell'!$O$2:$O$366+Annahmen!$B$10+'Kunde-SLP_Tagesmodell'!$T$2:$T$366*C$5))} -> 144080.54 | D6: {=SUM('Kunde-SLP_Tagesmodell'!$K$2:$K$366)-SUM('Kunde-SLP_Tagesmodell'!$P$2:$P$366)-SUM('Kunde-SLP_Tagesmodell'!$Q$2:$Q$366)-SUMPRODUCT(ABS('Kunde-SLP_Tagesmodell'!$I$2:$I$366*$B6),('Kunde-SLP_Tagesmodell'!$O$2:$O$366+Annahmen!$B$10+'Kunde-SLP_Tagesmodell'!$T$2:$T$366*D$5))} -> 138537.8 | E6: {=SUM('Kunde-SLP_Tagesmodell'!$K$2:$K$366)-SUM('Kunde-SLP_Tagesmodell'!$P$2:$P$366)-SUM('Kunde-SLP_Tagesmodell'!$Q$2:$Q$366)-SUMPRODUCT(ABS('Kunde-SLP_Tagesmodell'!$I$2:$I$366*$B6),('Kunde-SLP_Tagesmodell'!$O$2:$O$366+Annahmen!$B$10+'Kunde-SLP_Tagesmodell'!$T$2:$T$366*E$5))} -> 132995.05 | F6: {=SUM('Kunde-SLP_Tagesmodell'!$K$2:$K$366)-SUM('Kunde-SLP_Tagesmodell'!$P$2:$P$366)-SUM('Kunde-SLP_Tagesmodell'!$Q$2:$Q$366)-SUMPRODUCT(ABS('Kunde-SLP_Tagesmodell'!$I$2:$I$366*$B6),('Kunde-SLP_Tagesmodell'!$O$2:$O$366+Annahmen!$B$10+'Kunde-SLP_Tagesmodell'!$T$2:$T$366*F$5))} -> 127452.31 | G6: {=SUM('Kunde-SLP_Tagesmodell'!$K$2:$K$366)-SUM('Kunde-SLP_Tagesmodell'!$P$2:$P$366)-SUM('Kunde-SLP_Tagesmodell'!$Q$2:$Q$366)-SUMPRODUCT(ABS('Kunde-SLP_Tagesmodell'!$I$2:$I$366*$B6),('Kunde-SLP_Tagesmodell'!$O$2:$O$366+Annahmen!$B$10+'Kunde-SLP_Tagesmodell'!$T$2:$T$366*G$5))} -> 121909.57
B7: -0.1 | C7: {=SUM('Kunde-SLP_Tagesmodell'!$K$2:$K$366)-SUM('Kunde-SLP_Tagesmodell'!$P$2:$P$366)-SUM('Kunde-SLP_Tagesmodell'!$Q$2:$Q$366)-SUMPRODUCT(ABS('Kunde-SLP_Tagesmodell'!$I$2:$I$366*$B7),('Kunde-SLP_Tagesmodell'!$O$2:$O$366+Annahmen!$B$10+'Kunde-SLP_Tagesmodell'!$T$2:$T$366*C$5))} -> 193149.45 | D7: {=SUM('Kunde-SLP_Tagesmodell'!$K$2:$K$366)-SUM('Kunde-SLP_Tagesmodell'!$P$2:$P$366)-SUM('Kunde-SLP_Tagesmodell'!$Q$2:$Q$366)-SUMPRODUCT(ABS('Kunde-SLP_Tagesmodell'!$I$2:$I$366*$B7),('Kunde-SLP_Tagesmodell'!$O$2:$O$366+Annahmen!$B$10+'Kunde-SLP_Tagesmodell'!$T$2:$T$366*D$5))} -> 190378.08 | E7: {=SUM('Kunde-SLP_Tagesmodell'!$K$2:$K$366)-SUM('Kunde-SLP_Tagesmodell'!$P$2:$P$366)-SUM('Kunde-SLP_Tagesmodell'!$Q$2:$Q$366)-SUMPRODUCT(ABS('Kunde-SLP_Tagesmodell'!$I$2:$I$366*$B7),('Kunde-SLP_Tagesmodell'!$O$2:$O$366+Annahmen!$B$10+'Kunde-SLP_Tagesmodell'!$T$2:$T$366*E$5))} -> 187606.71 | F7: {=SUM('Kunde-SLP_Tagesmodell'!$K$2:$K$366)-SUM('Kunde-SLP_Tagesmodell'!$P$2:$P$366)-SUM('Kunde-SLP_Tagesmodell'!$Q$2:$Q$366)-SUMPRODUCT(ABS('Kunde-SLP_Tagesmodell'!$I$2:$I$366*$B7),('Kunde-SLP_Tagesmodell'!$O$2:$O$366+Annahmen!$B$10+'Kunde-SLP_Tagesmodell'!$T$2:$T$366*F$5))} -> 184835.34 | G7: {=SUM('Kunde-SLP_Tagesmodell'!$K$2:$K$366)-SUM('Kunde-SLP_Tagesmodell'!$P$2:$P$366)-SUM('Kunde-SLP_Tagesmodell'!$Q$2:$Q$366)-SUMPRODUCT(ABS('Kunde-SLP_Tagesmodell'!$I$2:$I$366*$B7),('Kunde-SLP_Tagesmodell'!$O$2:$O$366+Annahmen!$B$10+'Kunde-SLP_Tagesmodell'!$T$2:$T$366*G$5))} -> 182063.97
B8: -0.05 | C8: {=SUM('Kunde-SLP_Tagesmodell'!$K$2:$K$366)-SUM('Kunde-SLP_Tagesmodell'!$P$2:$P$366)-SUM('Kunde-SLP_Tagesmodell'!$Q$2:$Q$366)-SUMPRODUCT(ABS('Kunde-SLP_Tagesmodell'!$I$2:$I$366*$B8),('Kunde-SLP_Tagesmodell'!$O$2:$O$366+Annahmen!$B$10+'Kunde-SLP_Tagesmodell'!$T$2:$T$366*C$5))} -> 217683.91 | D8: {=SUM('Kunde-SLP_Tagesmodell'!$K$2:$K$366)-SUM('Kunde-SLP_Tagesmodell'!$P$2:$P$366)-SUM('Kunde-SLP_Tagesmodell'!$Q$2:$Q$366)-SUMPRODUCT(ABS('Kunde-SLP_Tagesmodell'!$I$2:$I$366*$B8),('Kunde-SLP_Tagesmodell'!$O$2:$O$366+Annahmen!$B$10+'Kunde-SLP_Tagesmodell'!$T$2:$T$366*D$5))} -> 216298.22 | E8: {=SUM('Kunde-SLP_Tagesmodell'!$K$2:$K$366)-SUM('Kunde-SLP_Tagesmodell'!$P$2:$P$366)-SUM('Kunde-SLP_Tagesmodell'!$Q$2:$Q$366)-SUMPRODUCT(ABS('Kunde-SLP_Tagesmodell'!$I$2:$I$366*$B8),('Kunde-SLP_Tagesmodell'!$O$2:$O$366+Annahmen!$B$10+'Kunde-SLP_Tagesmodell'!$T$2:$T$366*E$5))} -> 214912.54 | F8: {=SUM('Kunde-SLP_Tagesmodell'!$K$2:$K$366)-SUM('Kunde-SLP_Tagesmodell'!$P$2:$P$366)-SUM('Kunde-SLP_Tagesmodell'!$Q$2:$Q$366)-SUMPRODUCT(ABS('Kunde-SLP_Tagesmodell'!$I$2:$I$366*$B8),('Kunde-SLP_Tagesmodell'!$O$2:$O$366+Annahmen!$B$10+'Kunde-SLP_Tagesmodell'!$T$2:$T$366*F$5))} -> 213526.85 | G8: {=SUM('Kunde-SLP_Tagesmodell'!$K$2:$K$366)-SUM('Kunde-SLP_Tagesmodell'!$P$2:$P$366)-SUM('Kunde-SLP_Tagesmodell'!$Q$2:$Q$366)-SUMPRODUCT(ABS('Kunde-SLP_Tagesmodell'!$I$2:$I$366*$B8),('Kunde-SLP_Tagesmodell'!$O$2:$O$366+Annahmen!$B$10+'Kunde-SLP_Tagesmodell'!$T$2:$T$366*G$5))} -> 212141.17
B9: 0 | C9: {=SUM('Kunde-SLP_Tagesmodell'!$K$2:$K$366)-SUM('Kunde-SLP_Tagesmodell'!$P$2:$P$366)-SUM('Kunde-SLP_Tagesmodell'!$Q$2:$Q$366)-SUMPRODUCT(ABS('Kunde-SLP_Tagesmodell'!$I$2:$I$366*$B9),('Kunde-SLP_Tagesmodell'!$O$2:$O$366+Annahmen!$B$10+'Kunde-SLP_Tagesmodell'!$T$2:$T$366*C$5))} -> 242218.37 | D9: {=SUM('Kunde-SLP_Tagesmodell'!$K$2:$K$366)-SUM('Kunde-SLP_Tagesmodell'!$P$2:$P$366)-SUM('Kunde-SLP_Tagesmodell'!$Q$2:$Q$366)-SUMPRODUCT(ABS('Kunde-SLP_Tagesmodell'!$I$2:$I$366*$B9),('Kunde-SLP_Tagesmodell'!$O$2:$O$366+Annahmen!$B$10+'Kunde-SLP_Tagesmodell'!$T$2:$T$366*D$5))} -> 242218.37 | E9: {=SUM('Kunde-SLP_Tagesmodell'!$K$2:$K$366)-SUM('Kunde-SLP_Tagesmodell'!$P$2:$P$366)-SUM('Kunde-SLP_Tagesmodell'!$Q$2:$Q$366)-SUMPRODUCT(ABS('Kunde-SLP_Tagesmodell'!$I$2:$I$366*$B9),('Kunde-SLP_Tagesmodell'!$O$2:$O$366+Annahmen!$B$10+'Kunde-SLP_Tagesmodell'!$T$2:$T$366*E$5))} -> 242218.37 | F9: {=SUM('Kunde-SLP_Tagesmodell'!$K$2:$K$366)-SUM('Kunde-SLP_Tagesmodell'!$P$2:$P$366)-SUM('Kunde-SLP_Tagesmodell'!$Q$2:$Q$366)-SUMPRODUCT(ABS('Kunde-SLP_Tagesmodell'!$I$2:$I$366*$B9),('Kunde-SLP_Tagesmodell'!$O$2:$O$366+Annahmen!$B$10+'Kunde-SLP_Tagesmodell'!$T$2:$T$366*F$5))} -> 242218.37 | G9: {=SUM('Kunde-SLP_Tagesmodell'!$K$2:$K$366)-SUM('Kunde-SLP_Tagesmodell'!$P$2:$P$366)-SUM('Kunde-SLP_Tagesmodell'!$Q$2:$Q$366)-SUMPRODUCT(ABS('Kunde-SLP_Tagesmodell'!$I$2:$I$366*$B9),('Kunde-SLP_Tagesmodell'!$O$2:$O$366+Annahmen!$B$10+'Kunde-SLP_Tagesmodell'!$T$2:$T$366*G$5))} -> 242218.37
B10: 0.05 | C10: {=SUM('Kunde-SLP_Tagesmodell'!$K$2:$K$366)-SUM('Kunde-SLP_Tagesmodell'!$P$2:$P$366)-SUM('Kunde-SLP_Tagesmodell'!$Q$2:$Q$366)-SUMPRODUCT(ABS('Kunde-SLP_Tagesmodell'!$I$2:$I$366*$B10),('Kunde-SLP_Tagesmodell'!$O$2:$O$366+Annahmen!$B$10+'Kunde-SLP_Tagesmodell'!$T$2:$T$366*C$5))} -> 217683.91 | D10: {=SUM('Kunde-SLP_Tagesmodell'!$K$2:$K$366)-SUM('Kunde-SLP_Tagesmodell'!$P$2:$P$366)-SUM('Kunde-SLP_Tagesmodell'!$Q$2:$Q$366)-SUMPRODUCT(ABS('Kunde-SLP_Tagesmodell'!$I$2:$I$366*$B10),('Kunde-SLP_Tagesmodell'!$O$2:$O$366+Annahmen!$B$10+'Kunde-SLP_Tagesmodell'!$T$2:$T$366*D$5))} -> 216298.22 | E10: {=SUM('Kunde-SLP_Tagesmodell'!$K$2:$K$366)-SUM('Kunde-SLP_Tagesmodell'!$P$2:$P$366)-SUM('Kunde-SLP_Tagesmodell'!$Q$2:$Q$366)-SUMPRODUCT(ABS('Kunde-SLP_Tagesmodell'!$I$2:$I$366*$B10),('Kunde-SLP_Tagesmodell'!$O$2:$O$366+Annahmen!$B$10+'Kunde-SLP_Tagesmodell'!$T$2:$T$366*E$5))} -> 214912.54 | F10: {=SUM('Kunde-SLP_Tagesmodell'!$K$2:$K$366)-SUM('Kunde-SLP_Tagesmodell'!$P$2:$P$366)-SUM('Kunde-SLP_Tagesmodell'!$Q$2:$Q$366)-SUMPRODUCT(ABS('Kunde-SLP_Tagesmodell'!$I$2:$I$366*$B10),('Kunde-SLP_Tagesmodell'!$O$2:$O$366+Annahmen!$B$10+'Kunde-SLP_Tagesmodell'!$T$2:$T$366*F$5))} -> 213526.85 | G10: {=SUM('Kunde-SLP_Tagesmodell'!$K$2:$K$366)-SUM('Kunde-SLP_Tagesmodell'!$P$2:$P$366)-SUM('Kunde-SLP_Tagesmodell'!$Q$2:$Q$366)-SUMPRODUCT(ABS('Kunde-SLP_Tagesmodell'!$I$2:$I$366*$B10),('Kunde-SLP_Tagesmodell'!$O$2:$O$366+Annahmen!$B$10+'Kunde-SLP_Tagesmodell'!$T$2:$T$366*G$5))} -> 212141.17
B11: 0.1 | C11: {=SUM('Kunde-SLP_Tagesmodell'!$K$2:$K$366)-SUM('Kunde-SLP_Tagesmodell'!$P$2:$P$366)-SUM('Kunde-SLP_Tagesmodell'!$Q$2:$Q$366)-SUMPRODUCT(ABS('Kunde-SLP_Tagesmodell'!$I$2:$I$366*$B11),('Kunde-SLP_Tagesmodell'!$O$2:$O$366+Annahmen!$B$10+'Kunde-SLP_Tagesmodell'!$T$2:$T$366*C$5))} -> 193149.45 | D11: {=SUM('Kunde-SLP_Tagesmodell'!$K$2:$K$366)-SUM('Kunde-SLP_Tagesmodell'!$P$2:$P$366)-SUM('Kunde-SLP_Tagesmodell'!$Q$2:$Q$366)-SUMPRODUCT(ABS('Kunde-SLP_Tagesmodell'!$I$2:$I$366*$B11),('Kunde-SLP_Tagesmodell'!$O$2:$O$366+Annahmen!$B$10+'Kunde-SLP_Tagesmodell'!$T$2:$T$366*D$5))} -> 190378.08 | E11: {=SUM('Kunde-SLP_Tagesmodell'!$K$2:$K$366)-SUM('Kunde-SLP_Tagesmodell'!$P$2:$P$366)-SUM('Kunde-SLP_Tagesmodell'!$Q$2:$Q$366)-SUMPRODUCT(ABS('Kunde-SLP_Tagesmodell'!$I$2:$I$366*$B11),('Kunde-SLP_Tagesmodell'!$O$2:$O$366+Annahmen!$B$10+'Kunde-SLP_Tagesmodell'!$T$2:$T$366*E$5))} -> 187606.71 | F11: {=SUM('Kunde-SLP_Tagesmodell'!$K$2:$K$366)-SUM('Kunde-SLP_Tagesmodell'!$P$2:$P$366)-SUM('Kunde-SLP_Tagesmodell'!$Q$2:$Q$366)-SUMPRODUCT(ABS('Kunde-SLP_Tagesmodell'!$I$2:$I$366*$B11),('Kunde-SLP_Tagesmodell'!$O$2:$O$366+Annahmen!$B$10+'Kunde-SLP_Tagesmodell'!$T$2:$T$366*F$5))} -> 184835.34 | G11: {=SUM('Kunde-SLP_Tagesmodell'!$K$2:$K$366)-SUM('Kunde-SLP_Tagesmodell'!$P$2:$P$366)-SUM('Kunde-SLP_Tagesmodell'!$Q$2:$Q$366)-SUMPRODUCT(ABS('Kunde-SLP_Tagesmodell'!$I$2:$I$366*$B11),('Kunde-SLP_Tagesmodell'!$O$2:$O$366+Annahmen!$B$10+'Kunde-SLP_Tagesmodell'!$T$2:$T$366*G$5))} -> 182063.97
B12: 0.2 | C12: {=SUM('Kunde-SLP_Tagesmodell'!$K$2:$K$366)-SUM('Kunde-SLP_Tagesmodell'!$P$2:$P$366)-SUM('Kunde-SLP_Tagesmodell'!$Q$2:$Q$366)-SUMPRODUCT(ABS('Kunde-SLP_Tagesmodell'!$I$2:$I$366*$B12),('Kunde-SLP_Tagesmodell'!$O$2:$O$366+Annahmen!$B$10+'Kunde-SLP_Tagesmodell'!$T$2:$T$366*C$5))} -> 144080.54 | D12: {=SUM('Kunde-SLP_Tagesmodell'!$K$2:$K$366)-SUM('Kunde-SLP_Tagesmodell'!$P$2:$P$366)-SUM('Kunde-SLP_Tagesmodell'!$Q$2:$Q$366)-SUMPRODUCT(ABS('Kunde-SLP_Tagesmodell'!$I$2:$I$366*$B12),('Kunde-SLP_Tagesmodell'!$O$2:$O$366+Annahmen!$B$10+'Kunde-SLP_Tagesmodell'!$T$2:$T$366*D$5))} -> 138537.8 | E12: {=SUM('Kunde-SLP_Tagesmodell'!$K$2:$K$366)-SUM('Kunde-SLP_Tagesmodell'!$P$2:$P$366)-SUM('Kunde-SLP_Tagesmodell'!$Q$2:$Q$366)-SUMPRODUCT(ABS('Kunde-SLP_Tagesmodell'!$I$2:$I$366*$B12),('Kunde-SLP_Tagesmodell'!$O$2:$O$366+Annahmen!$B$10+'Kunde-SLP_Tagesmodell'!$T$2:$T$366*E$5))} -> 132995.05 | F12: {=SUM('Kunde-SLP_Tagesmodell'!$K$2:$K$366)-SUM('Kunde-SLP_Tagesmodell'!$P$2:$P$366)-SUM('Kunde-SLP_Tagesmodell'!$Q$2:$Q$366)-SUMPRODUCT(ABS('Kunde-SLP_Tagesmodell'!$I$2:$I$366*$B12),('Kunde-SLP_Tagesmodell'!$O$2:$O$366+Annahmen!$B$10+'Kunde-SLP_Tagesmodell'!$T$2:$T$366*F$5))} -> 127452.31 | G12: {=SUM('Kunde-SLP_Tagesmodell'!$K$2:$K$366)-SUM('Kunde-SLP_Tagesmodell'!$P$2:$P$366)-SUM('Kunde-SLP_Tagesmodell'!$Q$2:$Q$366)-SUMPRODUCT(ABS('Kunde-SLP_Tagesmodell'!$I$2:$I$366*$B12),('Kunde-SLP_Tagesmodell'!$O$2:$O$366+Annahmen!$B$10+'Kunde-SLP_Tagesmodell'!$T$2:$T$366*G$5))} -> 121909.57

Sheet BDEW-H25 Tagessummen
A1: BDEW H25 Tagessume je Monat | D1: Quelle: https://www.bdew.de/energie/standardlastprofile-strom/
A3: Monat | B3: Tagestyp | C3: Tagessumme | D3: Key (für Match)
A4: 1 | B4: SA | C4: =SUM(INDEX(Quelle_BDEW_H25!$5:$100,0,ROW()-1)) -> 2842.961 | D4: 1_SA
A5: 1 | B5: FT | C5: =SUM(INDEX(Quelle_BDEW_H25!$5:$100,0,ROW()-1)) -> 2903.033 | D5: 1_FT
A6: 1 | B6: WT | C6: =SUM(INDEX(Quelle_BDEW_H25!$5:$100,0,ROW()-1)) -> 2476.45 | D6: 1_WT
A7: 2 | B7: SA | C7: =SUM(INDEX(Quelle_BDEW_H25!$5:$100,0,ROW()-1)) -> 2844.567 | D7: 2_SA
A8: 2 | B8: FT | C8: =SUM(INDEX(Quelle_BDEW_H25!$5:$100,0,ROW()-1)) -> 2944.478 | D8: 2_FT
A9: 2 | B9: WT | C9: =SUM(INDEX(Quelle_BDEW_H25!$5:$100,0,ROW()-1)) -> 2448.516 | D9: 2_WT
A10: 3 | B10: SA | C10: =SUM(INDEX(Quelle_BDEW_H25!$5:$100,0,ROW()-1)) -> 2784.877 | D10: 3_SA
A11: 3 | B11: FT | C11: =SUM(INDEX(Quelle_BDEW_H25!$5:$100,0,ROW()-1)) -> 2866.433 | D11: 3_FT
A12: 3 | B12: WT | C12: =SUM(INDEX(Quelle_BDEW_H25!$5:$100,0,ROW()-1)) -> 2398.885 | D12: 3_WT
A13: 4 | B13: SA | C13: =SUM(INDEX(Quelle_BDEW_H25!$5:$100,0,ROW()-1)) -> 2961.768 | D13: 4_SA
A14: 4 | B14: FT | C14: =SUM(INDEX(Quelle_BDEW_H25!$5:$100,0,ROW()-1)) -> 3047.309 | D14: 4_FT
A15: 4 | B15: WT | C15: =SUM(INDEX(Quelle_BDEW_H25!$5:$100,0,ROW()-1)) -> 2554.952 | D15: 4_WT
... A39: 12 | B39: WT | C39: =SUM(INDEX(Quelle_BDEW_H25!$5:$100,0,ROW()-1)) -> 2536.519 | D39: 12_WT

Sheet Quelle_BDEW_H25
A1: Haushalt | C1: H25 | E1: normiert auf 1 Mio kWh Jahresverbrauch | I1: Bei Ausrollen der Profile ist die Dynamisierungsfunktion anzuwenden!
C3: 40909 | D3: 40909 | E3: 40909 | F3: 40940 | G3: 40940 | H3: 40940 | I3: 40969 | J3: 40969 | K3: 40969 | L3: 41000 | M3: 41000 | N3: 41000 | O3: 41030 | P3: 41030 | Q3: 41030 | R3: 41061 | S3: 41061 | T3: 41061 | U3: 41091 | V3: 41091 | W3: 41091 | X3: 41122 | Y3: 41122 | Z3: 41122 | AA3: 41153 | AB3: 41153 | AC3: 41153 | AD3: 41183 | AE3: 41183 | AF3: 41183 | AG3: 41214 | AH3: 41214 | AI3: 41214 | AJ3: 41244 | AK3: 41244 | AL3: 41244
B4: [kWh] | C4: SA | D4: FT | E4: WT | F4: SA | G4: FT | H4: WT | I4: SA | J4: FT | K4: WT | L4: SA | M4: FT | N4: WT | O4: SA | P4: FT | Q4: WT | R4: SA | S4: FT | T4: WT | U4: SA | V4: FT | W4: WT | X4: SA | Y4: FT | Z4: WT | AA4: SA | AB4: FT | AC4: WT | AD4: SA | AE4: FT | AF4: WT | AG4: SA | AH4: FT | AI4: WT | AJ4: SA | AK4: FT | AL4: WT
B5: 00:00-00:15 | C5: 22.152 | D5: 23.148 | E5: 20.126 | F5: 22.247 | G5: 23.03 | H5: 20.279 | I5: 21.857 | J5: 22.709 | K5: 19.602 | L5: 23.914 | M5: 24.952 | N5: 21.235 | O5: 24.619 | P5: 25.395 | Q5: 22.213 | R5: 26.983 | S5: 27.626 | T5: 24.566 | U5: 28.255 | V5: 28.737 | W5: 25.976 | X5: 26.762 | Y5: 27.556 | Z5: 24.849 | AA5: 23.55 | AB5: 25.014 | AC5: 21.296 | AD5: 22.87 | AE5: 23.558 | AF5: 20.509 | AG5: 21.707 | AH5: 22.535 | AI5: 19.583 | AJ5: 21.65 | AK5: 22.812 | AL5: 19.959
B6: 00:15-00:30 | C6: 20.809 | D6: 21.985 | E6: 18.915 | F6: 20.913 | G6: 21.688 | H6: 19.097 | I6: 20.478 | J6: 21.426 | K6: 18.418 | L6: 22.426 | M6: 23.419 | N6: 19.93 | O6: 23.08 | P6: 24.076 | Q6: 20.894 | R6: 25.584 | S6: 26.266 | T6: 23.272 | U6: 26.868 | V6: 27.379 | W6: 24.627 | X6: 25.412 | Y6: 26.314 | Z6: 23.605 | AA6: 22.282 | AB6: 23.683 | AC6: 20.197 | AD6: 21.534 | AE6: 22.195 | AF6: 19.261 | AG6: 20.333 | AH6: 21.231 | AI6: 18.36 | AJ6: 20.225 | AK6: 21.446 | AL6: 18.71
B7: 00:30-00:45 | C7: 19.757 | D7: 21.147 | E7: 17.959 | F7: 20.014 | G7: 20.821 | H7: 18.22 | I7: 19.823 | J7: 20.51 | K7: 17.849 | L7: 21.493 | M7: 22.371 | N7: 19.208 | O7: 22.073 | P7: 22.961 | Q7: 20.099 | R7: 24.444 | S7: 25.04 | T7: 22.285 | U7: 25.82 | V7: 26.3 | W7: 23.677 | X7: 24.561 | Y7: 25.227 | Z7: 22.732 | AA7: 21.458 | AB7: 22.735 | AC7: 19.484 | AD7: 20.761 | AE7: 21.169 | AF7: 18.58 | AG7: 19.296 | AH7: 20.274 | AI7: 17.387 | AJ7: 19.131 | AK7: 20.393 | AL7: 17.714
B8: 00:45-01:00 | C8: 18.889 | D8: 20.385 | E8: 17.202 | F8: 19.23 | G8: 20.06 | H8: 17.504 | I8: 19.045 | J8: 19.732 | K8: 17.125 | L8: 20.461 | M8: 21.343 | N8: 18.35 | O8: 20.956 | P8: 21.966 | Q8: 19.269 | R8: 23.317 | S8: 24.061 | T8: 21.359 | U8: 24.77 | V8: 25.299 | W8: 22.711 | X8: 23.525 | Y8: 24.307 | Z8: 21.924 | AA8: 20.445 | AB8: 21.814 | AC8: 18.739 | AD8: 19.81 | AE8: 20.225 | AF8: 17.779 | AG8: 18.38 | AH8: 19.385 | AI8: 16.601 | AJ8: 18.234 | AK8: 19.526 | AL8: 16.939
B9: 01:00-01:15 | C9: 18.217 | D9: 19.65 | E9: 16.612 | F9: 18.547 | G9: 19.356 | H9: 16.932 | I9: 18.327 | J9: 19.004 | K9: 16.584 | L9: 19.661 | M9: 20.445 | N9: 17.658 | O9: 20.167 | P9: 21.104 | Q9: 18.594 | R9: 22.374 | S9: 23.207 | T9: 20.683 | U9: 23.867 | V9: 24.452 | W9: 21.994 | X9: 22.842 | Y9: 23.501 | Z9: 21.275 | AA9: 19.743 | AB9: 21.023 | AC9: 18.186 | AD9: 18.994 | AE9: 19.446 | AF9: 17.176 | AG9: 17.729 | AH9: 18.648 | AI9: 16.044 | AJ9: 17.523 | AK9: 18.77 | AL9: 16.339
B10: 01:15-01:30 | C10: 17.53 | D10: 18.998 | E10: 16.077 | F10: 17.91 | G10: 18.708 | H10: 16.422 | I10: 17.756 | J10: 18.37 | K10: 16.13 | L10: 18.889 | M10: 19.695 | N10: 17.063 | O10: 19.364 | P10: 20.293 | Q10: 17.931 | R10: 21.562 | S10: 22.345 | T10: 19.963 | U10: 22.999 | V10: 23.532 | W10: 21.288 | X10: 22.101 | Y10: 22.692 | Z10: 20.63 | AA10: 19.006 | AB10: 20.187 | AC10: 17.559 | AD10: 18.273 | AE10: 18.716 | AF10: 16.61 | AG10: 17.151 | AH10: 18.035 | AI10: 15.52 | AJ10: 16.867 | AK10: 18.068 | AL10: 15.803
B11: 01:30-01:45 | C11: 16.988 | D11: 18.366 | E11: 15.796 | F11: 17.457 | G11: 18.112 | H11: 16.191 | I11: 17.345 | J11: 18.181 | K11: 15.883 | L11: 18.313 | M11: 19.283 | N11: 16.563 | O11: 18.689 | P11: 19.781 | Q11: 17.419 | R11: 20.807 | S11: 21.704 | T11: 19.347 | U11: 22.292 | V11: 22.911 | W11: 20.645 | X11: 21.377 | Y11: 22.126 | Z11: 20.1 | AA11: 18.287 | AB11: 19.563 | AC11: 17.069 | AD11: 17.659 | AE11: 18.354 | AF11: 16.146 | AG11: 16.715 | AH11: 17.531 | AI11: 15.269 | AJ11: 16.358 | AK11: 17.449 | AL11: 15.461
B12: 01:45-02:00 | C12: 16.399 | D12: 17.667 | E12: 15.3 | F12: 16.879 | G12: 17.474 | H12: 15.718 | I12: 16.779 | J12: 17.623 | K12: 15.476 | L12: 17.758 | M12: 18.657 | N12: 16.156 | O12: 18.091 | P12: 19.125 | Q12: 16.99 | R12: 20.258 | S12: 21.068 | T12: 18.946 | U12: 21.735 | V12: 22.278 | W12: 20.19 | X12: 20.887 | Y12: 21.476 | Z12: 19.651 | AA12: 17.779 | AB12: 19.015 | AC12: 16.676 | AD12: 17.077 | AE12: 17.7 | AF12: 15.744 | AG12: 16.184 | AH12: 16.923 | AI12: 14.857 | AJ12: 15.738 | AK12: 16.786 | AL12: 14.982
B13: 02:00-02:15 | C13: 16.199 | D13: 17.458 | E13: 15.287 | F13: 16.723 | G13: 17.413 | H13: 15.76 | I13: 16.666 | J13: 17.53 | K13: 15.464 | L13: 17.5 | M13: 18.326 | N13: 16.023 | O13: 17.862 | P13: 18.88 | Q13: 16.858 | R13: 19.852 | S13: 20.6 | T13: 18.67 | U13: 21.261 | V13: 21.815 | W13: 19.913 | X13: 20.537 | Y13: 21.074 | Z13: 19.425 | AA13: 17.488 | AB13: 18.669 | AC13: 16.51 | AD13: 16.839 | AE13: 17.174 | AF13: 15.63 | AG13: 16.016 | AH13: 16.77 | AI13: 14.874 | AJ13: 15.536 | AK13: 16.575 | AL13: 14.949
B14: 02:15-02:30 | C14: 15.893 | D14: 17.009 | E14: 15.143 | F14: 16.461 | G14: 17.088 | H14: 15.624 | I14: 16.478 | J14: 17.198 | K14: 15.342 | L14: 17.258 | M14: 18.037 | N14: 15.914 | O14: 17.584 | P14: 18.565 | Q14: 16.704 | R14: 19.574 | S14: 20.192 | T14: 18.489 | U14: 20.973 | V14: 21.318 | W14: 19.678 | X14: 20.195 | Y14: 20.644 | Z14: 19.212 | AA14: 17.218 | AB14: 18.329 | AC14: 16.352 | AD14: 16.608 | AE14: 16.911 | AF14: 15.501 | AG14: 15.764 | AH14: 16.41 | AI14: 14.735 | AJ14: 15.267 | AK14: 16.206 | AL14: 14.824
B15: 02:30-02:45 | C15: 15.66 | D15: 16.678 | E15: 15.025 | F15: 16.292 | G15: 16.829 | H15: 15.535 | I15: 16.298 | J15: 16.965 | K15: 15.244 | L15: 17.076 | M15: 17.754 | N15: 15.827 | O15: 17.442 | P15: 18.299 | Q15: 16.645 | R15: 19.284 | S15: 19.794 | T15: 18.314 | U15: 20.65 | V15: 20.97 | W15: 19.48 | X15: 19.927 | Y15: 20.315 | Z15: 19.024 | AA15: 17.079 | AB15: 18.11 | AC15: 16.276 | AD15: 16.455 | AE15: 16.629 | AF15: 15.398 | AG15: 15.574 | AH15: 16.201 | AI15: 14.66 | AJ15: 15.079 | AK15: 15.933 | AL15: 14.727
B16: 02:45-03:00 | C16: 15.442 | D16: 16.363 | E16: 14.934 | F16: 16.124 | G16: 16.648 | H16: 15.471 | I16: 16.168 | J16: 16.669 | K16: 15.17 | L16: 16.932 | M16: 17.531 | N16: 15.754 | O16: 17.295 | P16: 18.093 | Q16: 16.611 | R16: 19.072 | S16: 19.482 | T16: 18.186 | U16: 20.404 | V16: 20.642 | W16: 19.34 | X16: 19.768 | Y16: 20.015 | Z16: 18.892 | AA16: 16.988 | AB16: 17.838 | AC16: 16.189 | AD16: 16.309 | AE16: 16.405 | AF16: 15.358 | AG16: 15.404 | AH16: 16.031 | AI16: 14.684 | AJ16: 14.912 | AK16: 15.695 | AL16: 14.653
... B100: 23:45-00:00 | C100: 23.942 | D100: 21.67 | E100: 21.764 | F100: 24.174 | G100: 21.763 | H100: 21.929 | I100: 23.698 | J100: 21.228 | K100: 21.075 | L100: 25.849 | M100: 23.378 | N100: 23.25 | O100: 27.228 | P100: 23.878 | Q100: 24.235 | R100: 29.315 | S100: 26.171 | T100: 26.662 | U100: 30.267 | V100: 27.31 | W100: 27.888 | X100: 29.059 | Y100: 25.969 | Z100: 26.488 | AA100: 26.145 | AB100: 22.771 | AC100: 23.115 | AD100: 25.439 | AE100: 22.181 | AF100: 22.507 | AG100: 24.21 | AH100: 20.879 | AI100: 21.583 | AJ100: 24.158 | AK100: 21.995 | AL100: 21.911

Sheet Quelle_BDEW_Dynamisierung
A1: Dynamisches Profil | D1: Dynamisierungsfunktion

Sheet Quelle_SMARD_Preise_2025
A1: Datenkategorie: Großhandelspreise
A2: Region: DE-LU
A3: Zeitraum: 01.01.2025 00:00 - 01.01.2026 00:00
A4: Stand: 29.07.2026 17:50
A5: (c) Bundesnetzagentur | SMARD.de
A6: Auflösung: Tag
A7: Berechnete Auflösung: Deutschland/Luxemburg, ∅ Anrainer DE/LU, Belgien, Dänemark 1, Dänemark 2, Frankreich, Niederlande, Norwegen 2, Österreich, Polen, Schweden 4, Schweiz, Tschechien, DE/AT/LU, Italien (Nord), Slowenien, Ungarn
A8: Originalauflösung:
A10: Datum von | B10: Datum bis | C10: Deutschland/Luxemburg [€/MWh] | D10: ∅ Anrainer DE/LU [€/MWh] | E10: Belgien [€/MWh] | F10: Dänemark 1 [€/MWh] | G10: Dänemark 2 [€/MWh] | H10: Frankreich [€/MWh] | I10: Niederlande [€/MWh] | J10: Norwegen 2 [€/MWh] | K10: Österreich [€/MWh] | L10: Polen [€/MWh] | M10: Schweden 4 [€/MWh] | N10: Schweiz [€/MWh] | O10: Tschechien [€/MWh] | P10: DE/AT/LU [€/MWh] | Q10: Italien (Nord) [€/MWh] | R10: Slowenien [€/MWh] | S10: Ungarn [€/MWh]
A11: 45658 | B11: 02.01.2025 | C11: 0.95 | D11: 33.27 | E11: 22.14 | F11: 6.1 | G11: 6.28 | H11: 22.59 | I11: 35.69 | J11: 21.1 | K11: 96.2 | L11: 1.53 | M11: 6.34 | N11: 85.65 | O11: 62.4 | P11: - | Q11: 140.73 | R11: 88.35 | S11: 85.22
A12: 45659 | B12: 03.01.2025 | C12: 92.91 | D12: 101.09 | E12: 113.18 | F12: 82.76 | G12: 81.66 | H12: 107.69 | I12: 132.28 | J12: 83.18 | K12: 117.71 | L12: 81.47 | M12: 80.53 | N12: 124.64 | O12: 106.88 | P12: - | Q12: 139.33 | R12: 115.06 | S12: 115.79
A13: 45660 | B13: 04.01.2025 | C13: 89.94 | D13: 95.5 | E13: 120.11 | F13: 64.33 | G13: 64.65 | H13: 115.69 | I13: 114.81 | J13: 62.29 | K13: 115.08 | L13: 87.35 | M13: 64.88 | N13: 125.28 | O13: 115.98 | P13: - | Q13: 126.45 | R13: 118.06 | S13: 123.12
A14: 45661 | B14: 05.01.2025 | C14: 120.79 | D14: 116.65 | E14: 122.43 | F14: 120.79 | G14: 119.21 | H14: 121.74 | I14: 125.37 | J14: 93.24 | K14: 124.05 | L14: 115.46 | M14: 91.06 | N14: 127.64 | O14: 122.1 | P14: - | Q14: 145.38 | R14: 127.64 | S14: 138.75
A15: 45662 | B15: 06.01.2025 | C15: 72.24 | D15: 81.15 | E15: 56.89 | F15: 71.87 | G15: 72.39 | H15: 47.95 | I15: 65.68 | J15: 56.44 | K15: 125.98 | L15: 95.92 | M15: 63.45 | N15: 123.25 | O15: 112.78 | P15: - | Q15: 143.94 | R15: 107.95 | S15: 121.89
A16: 45663 | B16: 07.01.2025 | C16: 25.16 | D16: 57.97 | E16: 39.66 | F16: 24.58 | G16: 25.35 | H16: 35.44 | I16: 54.85 | J16: 29.62 | K16: 105.2 | L16: 59.47 | M16: 25.13 | N16: 123.9 | O16: 114.48 | P16: - | Q16: 136.43 | R16: 100.63 | S16: 119.02
A17: 45664 | B17: 08.01.2025 | C17: 58.29 | D17: 70.81 | E17: 78.04 | F17: 27.12 | G17: 25.34 | H17: 74.26 | I17: 82.19 | J17: 31.61 | K17: 109.57 | L17: 83.44 | M17: 23.04 | N17: 130.39 | O17: 113.91 | P17: - | Q17: 143.78 | R17: 110.68 | S17: 121.21
A18: 45665 | B18: 09.01.2025 | C18: 104.53 | D18: 98.29 | E18: 110.14 | F18: 75.45 | G18: 70.53 | H18: 104.33 | I18: 107.64 | J18: 71.18 | K18: 120.14 | L18: 106.97 | M18: 69.48 | N18: 128.6 | O18: 116.75 | P18: - | Q18: 133.21 | R18: 117.81 | S18: 119.34
A19: 45666 | B19: 10.01.2025 | C19: 121.53 | D19: 113.32 | E19: 106.39 | F19: 121.97 | G19: 120.86 | H19: 85.61 | I19: 115.21 | J19: 98.25 | K19: 122.6 | L19: 123.15 | M19: 101.78 | N19: 129.43 | O19: 121.24 | P19: - | Q19: 133.77 | R19: 123.5 | S19: 127.64
A20: 45667 | B20: 11.01.2025 | C20: 112.43 | D20: 108.62 | E20: 112.8 | F20: 111.42 | G20: 106.99 | H20: 112.96 | I20: 112.73 | J20: 88.92 | K20: 114.36 | L20: 109.4 | M20: 90.94 | N20: 121.92 | O20: 112.33 | P20: - | Q20: 131.1 | R20: 116.86 | S20: 120.72
A21: 45668 | B21: 12.01.2025 | C21: 101.89 | D21: 89.78 | E21: 108.89 | F21: 98.65 | G21: 64.26 | H21: 106.69 | I21: 112.65 | J21: 36.81 | K21: 106.1 | L21: 98.8 | M21: 35.7 | N21: 116.06 | O21: 102.93 | P21: - | Q21: 126.85 | R21: 107.42 | S21: 112.23
A22: 45669 | B22: 13.01.2025 | C22: 110.07 | D22: 103.11 | E22: 112.49 | F22: 110.07 | G22: 98.52 | H22: 108.26 | I22: 114.67 | J22: 71.36 | K22: 111.42 | L22: 109.84 | M22: 73.03 | N22: 113.71 | O22: 110.84 | P22: - | Q22: 113.35 | R22: 111.59 | S22: 111.71
... A375: 46022 | B375: 01.01.2026 | C375: 87.31 | D375: 91.18 | E375: 88.85 | F375: 86.23 | G375: 86.28 | H375: 89.07 | I375: 87.46 | J375: 85.68 | K375: 93.22 | L375: 104.68 | M375: 79.47 | N375: 104.53 | O375: 97.52 | P375: - | Q375: 109.85 | R375: 95.43 | S375: 100.12

Sheet Feiertage_Hessen_2025
A1: Gesetzliche Feiertage in Hessen 2025
A3: Feiertag | B3: Tag der Woche | C3: Datum
A4: Neujahr | B4: Mi | C4: 45658
A5: Karfreitag | B5: Fr | C5: 45765
A6: Ostermontag | B6: Mo | C6: 45768
A7: Tag der Arbeit | B7: Do | C7: 45778
A8: Christi Himmelfahrt | B8: Do | C8: 45806
A9: Pfingstmontag | B9: Mo | C9: 45817
A10: Fronleichnam | B10: Do | C10: 45827
A11: Tag der Deutschen Einheit | B11: Fr | C11: 45933
A12: Weihnachten | B12: Do | C12: 46016
A13: 2. Weihnachtstag | B13: Fr | C13: 46017
